{
  "manifestVersion": "3.2",
  "proxies": [
    {
      "address": "0xB6a211822649a61163b94cf46e6fCE46119D3E1b",
      "txHash": "0x53f97ab6f0b337d6c6e579f60911c519a75344a8a0cd67bdabd0edf87875ee2a",
      "kind": "transparent"
    },
    {
      "address": "0x467cAE742e855dEe7a999265c64f35758913e988",
      "txHash": "0xc10ed251f0b1855572e5e039f0577a1a862f55fcd00a80bbc0cc38904e7f1ae1",
      "kind": "uups"
    },
    {
      "address": "0xcA46FC562e8Ea82CCFA2Ff99aCD9D0F1dDc1CA87",
      "txHash": "0x0f757cda55235d9ade16ee5c221e136e8a60580774363e445f48b14a5e21fd6b",
      "kind": "uups"
    },
    {
      "address": "0xeA616854b8e87cB95628B5A65B9972d34D721710",
      "txHash": "0x725d1bb874f54cd259f664981b10376272e947d648ff943ce60d17a8bf43db19",
      "kind": "uups"
    }
  ],
  "impls": {
    "b8b2e08755b804c8b05b49b2be28ff6092006bbb0ac26bbf93b9fb876ff36150": {
      "address": "0x768c240Bc03a3517A08Ad12E2673aE434bE278d4",
      "txHash": "0x85609caea21392b0baf940f2a93710f8b7a3a7df7f82ac938fe1b005276807ed",
      "layout": {
        "solcVersion": "0.8.20",
        "storage": [
          {
            "label": "token",
            "offset": 0,
            "slot": "0",
            "type": "t_contract(IERC20)1515",
            "contract": "PredictionMarketMulti",
            "src": "contracts\\PredictionMarketMulti.sol:42"
          },
          {
            "label": "oracle",
            "offset": 0,
            "slot": "1",
            "type": "t_contract(OptimisticOracleV3Interface)2530",
            "contract": "PredictionMarketMulti",
            "src": "contracts\\PredictionMarketMulti.sol:43"
          },
          {
            "label": "assertionBond",
            "offset": 0,
            "slot": "2",
            "type": "t_uint256",
            "contract": "PredictionMarketMulti",
            "src": "contracts\\PredictionMarketMulti.sol:48"
          },
          {
            "label": "operators",
            "offset": 0,
            "slot": "3",
            "type": "t_mapping(t_address,t_bool)",
            "contract": "PredictionMarketMulti",
            "src": "contracts\\PredictionMarketMulti.sol:55"
          },
          {
            "label": "marketCount",
            "offset": 0,
            "slot": "4",
            "type": "t_uint256",
            "contract": "PredictionMarketMulti",
            "src": "contracts\\PredictionMarketMulti.sol:79"
          },
          {
            "label": "markets",
            "offset": 0,
            "slot": "5",
            "type": "t_mapping(t_uint256,t_struct(Market)2593_storage)",
            "contract": "PredictionMarketMulti",
            "src": "contracts\\PredictionMarketMulti.sol:80"
          },
          {
            "label": "positions",
            "offset": 0,
            "slot": "6",
            "type": "t_mapping(t_uint256,t_mapping(t_address,t_struct(Position)2600_storage))",
            "contract": "PredictionMarketMulti",
            "src": "contracts\\PredictionMarketMulti.sol:81"
          },
          {
            "label": "assertionToMarket",
            "offset": 0,
            "slot": "7",
            "type": "t_mapping(t_bytes32,t_uint256)",
            "contract": "PredictionMarketMulti",
            "src": "contracts\\PredictionMarketMulti.sol:82"
          },
          {
            "label": "userBalances",
            "offset": 0,
            "slot": "8",
            "type": "t_mapping(t_address,t_uint256)",
            "contract": "PredictionMarketMulti",
            "src": "contracts\\PredictionMarketMulti.sol:85"
          }
        ],
        "types": {
          "t_address": {
            "label": "address",
            "numberOfBytes": "20"
          },
          "t_bool": {
            "label": "bool",
            "numberOfBytes": "1"
          },
          "t_struct(InitializableStorage)73_storage": {
            "label": "struct Initializable.InitializableStorage",
            "members": [
              {
                "label": "_initialized",
                "type": "t_uint64",
                "offset": 0,
                "slot": "0"
              },
              {
                "label": "_initializing",
                "type": "t_bool",
                "offset": 8,
                "slot": "0"
              }
            ],
            "numberOfBytes": "32"
          },
          "t_struct(OwnableStorage)13_storage": {
            "label": "struct OwnableUpgradeable.OwnableStorage",
            "members": [
              {
                "label": "_owner",
                "type": "t_address",
                "offset": 0,
                "slot": "0"
              }
            ],
            "numberOfBytes": "32"
          },
          "t_struct(ReentrancyGuardStorage)163_storage": {
            "label": "struct ReentrancyGuardUpgradeable.ReentrancyGuardStorage",
            "members": [
              {
                "label": "_status",
                "type": "t_uint256",
                "offset": 0,
                "slot": "0"
              }
            ],
            "numberOfBytes": "32"
          },
          "t_uint256": {
            "label": "uint256",
            "numberOfBytes": "32"
          },
          "t_uint64": {
            "label": "uint64",
            "numberOfBytes": "8"
          },
          "t_array(t_string_storage)dyn_storage": {
            "label": "string[]",
            "numberOfBytes": "32"
          },
          "t_array(t_uint256)dyn_storage": {
            "label": "uint256[]",
            "numberOfBytes": "32"
          },
          "t_bytes32": {
            "label": "bytes32",
            "numberOfBytes": "32"
          },
          "t_contract(IERC20)1515": {
            "label": "contract IERC20",
            "numberOfBytes": "20"
          },
          "t_contract(OptimisticOracleV3Interface)2530": {
            "label": "contract OptimisticOracleV3Interface",
            "numberOfBytes": "20"
          },
          "t_mapping(t_address,t_bool)": {
            "label": "mapping(address => bool)",
            "numberOfBytes": "32"
          },
          "t_mapping(t_address,t_struct(Position)2600_storage)": {
            "label": "mapping(address => struct PredictionMarketMulti.Position)",
            "numberOfBytes": "32"
          },
          "t_mapping(t_address,t_uint256)": {
            "label": "mapping(address => uint256)",
            "numberOfBytes": "32"
          },
          "t_mapping(t_bytes32,t_uint256)": {
            "label": "mapping(bytes32 => uint256)",
            "numberOfBytes": "32"
          },
          "t_mapping(t_uint256,t_mapping(t_address,t_struct(Position)2600_storage))": {
            "label": "mapping(uint256 => mapping(address => struct PredictionMarketMulti.Position))",
            "numberOfBytes": "32"
          },
          "t_mapping(t_uint256,t_struct(Market)2593_storage)": {
            "label": "mapping(uint256 => struct PredictionMarketMulti.Market)",
            "numberOfBytes": "32"
          },
          "t_mapping(t_uint256,t_uint256)": {
            "label": "mapping(uint256 => uint256)",
            "numberOfBytes": "32"
          },
          "t_string_storage": {
            "label": "string",
            "numberOfBytes": "32"
          },
          "t_struct(Market)2593_storage": {
            "label": "struct PredictionMarketMulti.Market",
            "members": [
              {
                "label": "question",
                "type": "t_string_storage",
                "offset": 0,
                "slot": "0"
              },
              {
                "label": "outcomes",
                "type": "t_array(t_string_storage)dyn_storage",
                "offset": 0,
                "slot": "1"
              },
              {
                "label": "shares",
                "type": "t_array(t_uint256)dyn_storage",
                "offset": 0,
                "slot": "2"
              },
              {
                "label": "outcomeCount",
                "type": "t_uint256",
                "offset": 0,
                "slot": "3"
              },
              {
                "label": "endTime",
                "type": "t_uint256",
                "offset": 0,
                "slot": "4"
              },
              {
                "label": "liquidityParam",
                "type": "t_uint256",
                "offset": 0,
                "slot": "5"
              },
              {
                "label": "resolved",
                "type": "t_bool",
                "offset": 0,
                "slot": "6"
              },
              {
                "label": "winningOutcome",
                "type": "t_uint256",
                "offset": 0,
                "slot": "7"
              },
              {
                "label": "subsidyPool",
                "type": "t_uint256",
                "offset": 0,
                "slot": "8"
              },
              {
                "label": "assertionId",
                "type": "t_bytes32",
                "offset": 0,
                "slot": "9"
              },
              {
                "label": "assertionPending",
                "type": "t_bool",
                "offset": 0,
                "slot": "10"
              },
              {
                "label": "asserter",
                "type": "t_address",
                "offset": 1,
                "slot": "10"
              },
              {
                "label": "assertedOutcome",
                "type": "t_uint256",
                "offset": 0,
                "slot": "11"
              }
            ],
            "numberOfBytes": "384"
          },
          "t_struct(Position)2600_storage": {
            "label": "struct PredictionMarketMulti.Position",
            "members": [
              {
                "label": "shares",
                "type": "t_mapping(t_uint256,t_uint256)",
                "offset": 0,
                "slot": "0"
              },
              {
                "label": "claimed",
                "type": "t_bool",
                "offset": 0,
                "slot": "1"
              }
            ],
            "numberOfBytes": "64"
          }
        },
        "namespaces": {
          "erc7201:openzeppelin.storage.ReentrancyGuard": [
            {
              "contract": "ReentrancyGuardUpgradeable",
              "label": "_status",
              "type": "t_uint256",
              "src": "@openzeppelin\\contracts-upgradeable\\utils\\ReentrancyGuardUpgradeable.sol:43",
              "offset": 0,
              "slot": "0"
            }
          ],
          "erc7201:openzeppelin.storage.Ownable": [
            {
              "contract": "OwnableUpgradeable",
              "label": "_owner",
              "type": "t_address",
              "src": "@openzeppelin\\contracts-upgradeable\\access\\OwnableUpgradeable.sol:24",
              "offset": 0,
              "slot": "0"
            }
          ],
          "erc7201:openzeppelin.storage.Initializable": [
            {
              "contract": "Initializable",
              "label": "_initialized",
              "type": "t_uint64",
              "src": "@openzeppelin\\contracts-upgradeable\\proxy\\utils\\Initializable.sol:69",
              "offset": 0,
              "slot": "0"
            },
            {
              "contract": "Initializable",
              "label": "_initializing",
              "type": "t_bool",
              "src": "@openzeppelin\\contracts-upgradeable\\proxy\\utils\\Initializable.sol:73",
              "offset": 8,
              "slot": "0"
            }
          ]
        }
      }
    },
    "e26efefa1c7850f19d9d462a0b4d4078e6fbaa71f930476cfd081014e1faf62e": {
      "address": "0xf041fb35fBa795a56C49fb73924d54e7a5b0406E",
      "txHash": "0x5beb689b533a10d5e21ae033f3d5757c10dc99cb6413704c9351ee56d3eda650",
      "layout": {
        "solcVersion": "0.8.22",
        "storage": [
          {
            "label": "token",
            "offset": 0,
            "slot": "0",
            "type": "t_contract(IERC20)2032",
            "contract": "PredictionMarketMultiV2",
            "src": "contracts\\PredictionMarketMultiV2.sol:56"
          },
          {
            "label": "oracle",
            "offset": 0,
            "slot": "1",
            "type": "t_contract(OptimisticOracleV3Interface)5462",
            "contract": "PredictionMarketMultiV2",
            "src": "contracts\\PredictionMarketMultiV2.sol:57"
          },
          {
            "label": "assertionBond",
            "offset": 0,
            "slot": "2",
            "type": "t_uint256",
            "contract": "PredictionMarketMultiV2",
            "src": "contracts\\PredictionMarketMultiV2.sol:62"
          },
          {
            "label": "operators",
            "offset": 0,
            "slot": "3",
            "type": "t_mapping(t_address,t_bool)",
            "contract": "PredictionMarketMultiV2",
            "src": "contracts\\PredictionMarketMultiV2.sol:69"
          },
          {
            "label": "marketCount",
            "offset": 0,
            "slot": "4",
            "type": "t_uint256",
            "contract": "PredictionMarketMultiV2",
            "src": "contracts\\PredictionMarketMultiV2.sol:93"
          },
          {
            "label": "markets",
            "offset": 0,
            "slot": "5",
            "type": "t_mapping(t_uint256,t_struct(Market)5529_storage)",
            "contract": "PredictionMarketMultiV2",
            "src": "contracts\\PredictionMarketMultiV2.sol:94"
          },
          {
            "label": "positions",
            "offset": 0,
            "slot": "6",
            "type": "t_mapping(t_uint256,t_mapping(t_address,t_struct(Position)5536_storage))",
            "contract": "PredictionMarketMultiV2",
            "src": "contracts\\PredictionMarketMultiV2.sol:95"
          },
          {
            "label": "assertionToMarket",
            "offset": 0,
            "slot": "7",
            "type": "t_mapping(t_bytes32,t_uint256)",
            "contract": "PredictionMarketMultiV2",
            "src": "contracts\\PredictionMarketMultiV2.sol:96"
          },
          {
            "label": "userBalances",
            "offset": 0,
            "slot": "8",
            "type": "t_mapping(t_address,t_uint256)",
            "contract": "PredictionMarketMultiV2",
            "src": "contracts\\PredictionMarketMultiV2.sol:99"
          }
        ],
        "types": {
          "t_address": {
            "label": "address",
            "numberOfBytes": "20"
          },
          "t_bool": {
            "label": "bool",
            "numberOfBytes": "1"
          },
          "t_struct(InitializableStorage)73_storage": {
            "label": "struct Initializable.InitializableStorage",
            "members": [
              {
                "label": "_initialized",
                "type": "t_uint64",
                "offset": 0,
                "slot": "0"
              },
              {
                "label": "_initializing",
                "type": "t_bool",
                "offset": 8,
                "slot": "0"
              }
            ],
            "numberOfBytes": "32"
          },
          "t_struct(OwnableStorage)13_storage": {
            "label": "struct OwnableUpgradeable.OwnableStorage",
            "members": [
              {
                "label": "_owner",
                "type": "t_address",
                "offset": 0,
                "slot": "0"
              }
            ],
            "numberOfBytes": "32"
          },
          "t_struct(ReentrancyGuardStorage)226_storage": {
            "label": "struct ReentrancyGuardUpgradeable.ReentrancyGuardStorage",
            "members": [
              {
                "label": "_status",
                "type": "t_uint256",
                "offset": 0,
                "slot": "0"
              }
            ],
            "numberOfBytes": "32"
          },
          "t_uint256": {
            "label": "uint256",
            "numberOfBytes": "32"
          },
          "t_uint64": {
            "label": "uint64",
            "numberOfBytes": "8"
          },
          "t_array(t_string_storage)dyn_storage": {
            "label": "string[]",
            "numberOfBytes": "32"
          },
          "t_array(t_uint256)dyn_storage": {
            "label": "uint256[]",
            "numberOfBytes": "32"
          },
          "t_bytes32": {
            "label": "bytes32",
            "numberOfBytes": "32"
          },
          "t_contract(IERC20)2032": {
            "label": "contract IERC20",
            "numberOfBytes": "20"
          },
          "t_contract(OptimisticOracleV3Interface)5462": {
            "label": "contract OptimisticOracleV3Interface",
            "numberOfBytes": "20"
          },
          "t_mapping(t_address,t_bool)": {
            "label": "mapping(address => bool)",
            "numberOfBytes": "32"
          },
          "t_mapping(t_address,t_struct(Position)5536_storage)": {
            "label": "mapping(address => struct PredictionMarketMultiV2.Position)",
            "numberOfBytes": "32"
          },
          "t_mapping(t_address,t_uint256)": {
            "label": "mapping(address => uint256)",
            "numberOfBytes": "32"
          },
          "t_mapping(t_bytes32,t_uint256)": {
            "label": "mapping(bytes32 => uint256)",
            "numberOfBytes": "32"
          },
          "t_mapping(t_uint256,t_mapping(t_address,t_struct(Position)5536_storage))": {
            "label": "mapping(uint256 => mapping(address => struct PredictionMarketMultiV2.Position))",
            "numberOfBytes": "32"
          },
          "t_mapping(t_uint256,t_struct(Market)5529_storage)": {
            "label": "mapping(uint256 => struct PredictionMarketMultiV2.Market)",
            "numberOfBytes": "32"
          },
          "t_mapping(t_uint256,t_uint256)": {
            "label": "mapping(uint256 => uint256)",
            "numberOfBytes": "32"
          },
          "t_string_storage": {
            "label": "string",
            "numberOfBytes": "32"
          },
          "t_struct(Market)5529_storage": {
            "label": "struct PredictionMarketMultiV2.Market",
            "members": [
              {
                "label": "question",
                "type": "t_string_storage",
                "offset": 0,
                "slot": "0"
              },
              {
                "label": "outcomes",
                "type": "t_array(t_string_storage)dyn_storage",
                "offset": 0,
                "slot": "1"
              },
              {
                "label": "shares",
                "type": "t_array(t_uint256)dyn_storage",
                "offset": 0,
                "slot": "2"
              },
              {
                "label": "outcomeCount",
                "type": "t_uint256",
                "offset": 0,
                "slot": "3"
              },
              {
                "label": "endTime",
                "type": "t_uint256",
                "offset": 0,
                "slot": "4"
              },
              {
                "label": "liquidityParam",
                "type": "t_uint256",
                "offset": 0,
                "slot": "5"
              },
              {
                "label": "resolved",
                "type": "t_bool",
                "offset": 0,
                "slot": "6"
              },
              {
                "label": "winningOutcome",
                "type": "t_uint256",
                "offset": 0,
                "slot": "7"
              },
              {
                "label": "subsidyPool",
                "type": "t_uint256",
                "offset": 0,
                "slot": "8"
              },
              {
                "label": "assertionId",
                "type": "t_bytes32",
                "offset": 0,
                "slot": "9"
              },
              {
                "label": "assertionPending",
                "type": "t_bool",
                "offset": 0,
                "slot": "10"
              },
              {
                "label": "asserter",
                "type": "t_address",
                "offset": 1,
                "slot": "10"
              },
              {
                "label": "assertedOutcome",
                "type": "t_uint256",
                "offset": 0,
                "slot": "11"
              },
              {
                "label": "deleted",
                "type": "t_bool",
                "offset": 0,
                "slot": "12"
              }
            ],
            "numberOfBytes": "416"
          },
          "t_struct(Position)5536_storage": {
            "label": "struct PredictionMarketMultiV2.Position",
            "members": [
              {
                "label": "shares",
                "type": "t_mapping(t_uint256,t_uint256)",
                "offset": 0,
                "slot": "0"
              },
              {
                "label": "claimed",
                "type": "t_bool",
                "offset": 0,
                "slot": "1"
              }
            ],
            "numberOfBytes": "64"
          }
        },
        "namespaces": {
          "erc7201:openzeppelin.storage.ReentrancyGuard": [
            {
              "contract": "ReentrancyGuardUpgradeable",
              "label": "_status",
              "type": "t_uint256",
              "src": "@openzeppelin\\contracts-upgradeable\\utils\\ReentrancyGuardUpgradeable.sol:43",
              "offset": 0,
              "slot": "0"
            }
          ],
          "erc7201:openzeppelin.storage.Ownable": [
            {
              "contract": "OwnableUpgradeable",
              "label": "_owner",
              "type": "t_address",
              "src": "@openzeppelin\\contracts-upgradeable\\access\\OwnableUpgradeable.sol:24",
              "offset": 0,
              "slot": "0"
            }
          ],
          "erc7201:openzeppelin.storage.Initializable": [
            {
              "contract": "Initializable",
              "label": "_initialized",
              "type": "t_uint64",
              "src": "@openzeppelin\\contracts-upgradeable\\proxy\\utils\\Initializable.sol:69",
              "offset": 0,
              "slot": "0"
            },
            {
              "contract": "Initializable",
              "label": "_initializing",
              "type": "t_bool",
              "src": "@openzeppelin\\contracts-upgradeable\\proxy\\utils\\Initializable.sol:73",
              "offset": 8,
              "slot": "0"
            }
          ]
        }
      }
    }
  }
}
